{
    "Abomasnow": {
        "level": 82,
        "abilities": [
            "Snow Warning"
        ],
        "items": [
            "Assault Vest",
            "Light Clay"
        ],
        "moves": [
            "Aurora Veil",
            "Blizzard",
            "Earthquake",
            "Ice Shard",
            "Wood Hammer"
        ],
        "types": [
            "grass",
            "ice"
        ]
    },
    "Amoonguss": {
        "level": 84,
        "abilities": [
            "Regenerator"
        ],
        "items": [
            "Black Sludge"
        ],
        "moves": [
            "Clear Smog",
            "Giga Drain",
            "Sludge Bomb",
            "Spore",
            "Synthesis",
            "Toxic"
        ],
        "evs": {
            "atk": 0
        },
        "ivs": {
            "atk": 0
        },
        "types": [
            "grass",
            "poison"
        ]
    },
    "Appletun": {
        "level": 90,
        "abilities": [
            "Thick Fat"
        ],
        "items": [
            "Leftovers"
        ],
        "moves": [
            "Apple Acid",
            "Dragon Pulse",
            "Leech Seed",
            "Recover"
        ],
        "evs": {
            "atk": 0
        },
        "ivs": {
            "atk": 0
        },
        "types": [
            "grass",
            "dragon"
        ]
    },
    "Bellossom": {
        "level": 82,
        "abilities": [
            "Chlorophyll"
        ],
        "items": [
            "Leftovers"
        ],
        "moves": [
            "Giga Drain",
            "Moonblast",
            "Quiver Dance",
            "Sleep Powder",
            "Strength Sap"
        ],
        "evs": {
            "atk": 0
        },
        "ivs": {
            "atk": 0
        },
        "types": [
            "grass"
        ]
    },
    "Calyrex": {
        "level": 88,
        "abilities": [
            "Unnerve"
        ],
        "items": [
            "Leftovers"
        ],
        "moves": [
            "Calm Mind",
            "Giga Drain",
            "Leech Seed",
            "Psyshock",
            "Substitute"
        ],
        "evs": {
            "atk": 0
        },
        "ivs": {
            "atk": 0
        },
        "types": [
            "psychic",
            "grass"
        ]
    },
    "Celebi": {
        "level": 82,
        "abilities": [
            "Natural Cure"
        ],
        "items": [
            "Choice Scarf",
            "Choice Specs",
            "Leftovers",
            "Life Orb"
        ],
        "moves": [
            "Earth Power",
            "Giga Drain",
            "Leaf Storm",
            "Nasty Plot",
            "Psychic",
            "Recover",
            "Stealth Rock",
            "U-turn"
        ],
        "evs": {
            "atk": 0
        },
        "ivs": {
            "atk": 0
        },
        "types": [
            "psychic",
            "grass"
        ]
    },
    "Cherrim": {
        "level": 93,
        "abilities": [
            "Flower Gift"
        ],
        "items": [
            "Choice Scarf"
        ],
        "moves": [
            "Dazzling Gleam",
            "Energy Ball",
            "Healing Wish",
            "Petal Dance",
            "Pollen Puff"
        ],
        "evs": {
            "atk": 0
        },
        "ivs": {
            "atk": 0
        },
        "types": [
            "grass"
        ]
    },
    "Cradily": {
        "level": 86,
        "abilities": [
            "Storm Drain"
        ],
        "items": [
            "Leftovers"
        ],
        "moves": [
            "Power Whip",
            "Recover",
            "Stealth Rock",
            "Stone Edge",
            "Swords Dance",
            "Toxic"
        ],
        "types": [
            "rock",
            "grass"
        ]
    },
    "Decidueye": {
        "level": 86,
        "abilities": [
            "Overgrow"
        ],
        "items": [
            "Choice Band",
            "Life Orb",
            "Lum Berry"
        ],
        "moves": [
            "Brave Bird",
            "Leaf Blade",
            "Poltergeist",
            "Roost",
            "Shadow Sneak",
            "Swords Dance"
        ],
        "types": [
            "grass",
            "ghost"
        ]
    },
    "Dhelmise": {
        "level": 86,
        "abilities": [
            "Steelworker"
        ],
        "items": [
            "Assault Vest",
            "Choice Band",
            "Lum Berry"
        ],
        "moves": [
            "Anchor Shot",
            "Earthquake",
            "Poltergeist",
            "Power Whip",
            "Rapid Spin",
            "Swords Dance"
        ],
        "types": [
            "ghost",
            "grass"
        ]
    },
    "Eldegoss": {
        "level": 90,
        "abilities": [
            "Regenerator"
        ],
        "items": [
            "Heavy-Duty Boots",
            "Leftovers"
        ],
        "moves": [
            "Energy Ball",
            "Leech Seed",
            "Pollen Puff",
            "Rapid Spin",
            "Sleep Powder"
        ],
        "evs": {
            "atk": 0
        },
        "ivs": {
            "atk": 0
        },
        "types": [
            "grass"
        ]
    },
    "Exeggutor": {
        "level": 86,
        "abilities": [
            "Chlorophyll",
            "Harvest"
        ],
        "items": [
            "Leftovers",
            "Sitrus Berry"
        ],
        "moves": [
            "Giga Drain",
            "Leech Seed",
            "Psychic",
            "Sleep Powder",
            "Substitute"
        ],
        "evs": {
            "atk": 0
        },
        "ivs": {
            "atk": 0
        },
        "types": [
            "grass",
            "psychic"
        ]
    },
    "Ferrothorn": {
        "level": 78,
        "abilities": [
            "Iron Barbs"
        ],
        "items": [
            "Leftovers"
        ],
        "moves": [
            "Gyro Ball",
            "Knock Off",
            "Leech Seed",
            "Power Whip",
            "Protect",
            "Spikes",
            "Stealth Rock"
        ],
        "evs": {
            "spe": 0
        },
        "ivs": {
            "spe": 0
        },
        "types": [
            "grass",
            "steel"
        ]
    },
    "Flapple": {
        "level": 84,
        "abilities": [
            "Hustle"
        ],
        "items": [
            "Choice Band",
            "Focus Sash",
            "Life Orb"
        ],
        "moves": [
            "Dragon Dance",
            "Grav Apple",
            "Outrage",
            "Sucker Punch",
            "U-turn"
        ],
        "types": [
            "grass",
            "dragon"
        ]
    },
    "Gourgeist": {
        "level": 84,
        "abilities": [
            "Frisk"
        ],
        "items": [
            "Leftovers",
            "Life Orb"
        ],
        "moves": [
            "Poltergeist",
            "Power Whip",
            "Shadow Sneak",
            "Synthesis",
            "Will-O-Wisp"
        ],
        "types": [
            "ghost",
            "grass"
        ]
    },
    "Kartana": {
        "level": 74,
        "abilities": [
            "Beast Boost"
        ],
        "items": [
            "Choice Band",
            "Life Orb"
        ],
        "moves": [
            "Knock Off",
            "Leaf Blade",
            "Sacred Sword",
            "Smart Strike",
            "Swords Dance"
        ],
        "types": [
            "grass",
            "steel"
        ]
    },
    "Leafeon": {
        "level": 86,
        "abilities": [
            "Chlorophyll"
        ],
        "items": [
            "Choice Band",
            "Choice Scarf",
            "Life Orb",
            "Lum Berry"
        ],
        "moves": [
            "Double-Edge",
            "Knock Off",
            "Leaf Blade",
            "Swords Dance",
            "Synthesis",
            "X-Scissor"
        ],
        "types": [
            "grass"
        ]
    },
    "Lilligant": {
        "level": 84,
        "abilities": [
            "Chlorophyll",
            "Own Tempo"
        ],
        "items": [
            "Leftovers",
            "Life Orb"
        ],
        "moves": [
            "Giga Drain",
            "Petal Dance",
            "Pollen Puff",
            "Quiver Dance",
            "Sleep Powder"
        ],
        "evs": {
            "atk": 0
        },
        "ivs": {
            "atk": 0
        },
        "types": [
            "grass"
        ]
    },
    "Ludicolo": {
        "level": 86,
        "abilities": [
            "Swift Swim"
        ],
        "items": [
            "Choice Specs",
            "Life Orb"
        ],
        "moves": [
            "Giga Drain",
            "Hydro Pump",
            "Ice Beam",
            "Rain Dance",
            "Scald"
        ],
        "evs": {
            "atk": 0
        },
        "ivs": {
            "atk": 0
        },
        "types": [
            "water",
            "grass"
        ]
    },
    "Lurantis": {
        "level": 86,
        "abilities": [
            "Contrary"
        ],
        "items": [
            "Leftovers",
            "Life Orb"
        ],
        "moves": [
            "Defog",
            "Knock Off",
            "Leaf Storm",
            "Superpower",
            "Synthesis"
        ],
        "types": [
            "grass"
        ]
    },
    "Maractus": {
        "level": 94,
        "abilities": [
            "Chlorophyll",
            "Storm Drain",
            "Water Absorb"
        ],
        "items": [
            "Focus Sash",
            "Leftovers"
        ],
        "moves": [
            "Energy Ball",
            "Knock Off",
            "Leech Seed",
            "Spikes",
            "Spiky Shield",
            "Toxic"
        ],
        "evs": {
            "atk": 0
        },
        "ivs": {
            "atk": 0
        },
        "types": [
            "grass"
        ]
    },
    "Rillaboom": {
        "level": 78,
        "abilities": [
            "Grassy Surge"
        ],
        "items": [
            "Choice Band"
        ],
        "moves": [
            "Grassy Glide",
            "High Horsepower",
            "Knock Off",
            "U-turn",
            "Wood Hammer"
        ],
        "types": [
            "grass"
        ]
    },
    "Roserade": {
        "level": 84,
        "abilities": [
            "Natural Cure"
        ],
        "items": [
            "Black Sludge",
            "Focus Sash"
        ],
        "moves": [
            "Leaf Storm",
            "Sleep Powder",
            "Sludge Bomb",
            "Spikes",
            "Synthesis",
            "Toxic Spikes"
        ],
        "evs": {
            "atk": 0
        },
        "ivs": {
            "atk": 0
        },
        "types": [
            "grass",
            "poison"
        ]
    },
    "Sceptile": {
        "level": 86,
        "abilities": [
            "Overgrow"
        ],
        "items": [
            "Leftovers",
            "Life Orb"
        ],
        "moves": [
            "Earthquake",
            "Focus Blast",
            "Giga Drain",
            "Leaf Storm",
            "Leech Seed",
            "Rock Slide",
            "Substitute"
        ],
        "evs": {
            "atk": 0
        },
        "ivs": {
            "atk": 0
        },
        "types": [
            "grass"
        ]
    },
    "Shiftry": {
        "level": 86,
        "abilities": [
            "Chlorophyll"
        ],
        "items": [
            "Focus Sash",
            "Life Orb"
        ],
        "moves": [
            "Dark Pulse",
            "Defog",
            "Heat Wave",
            "Leaf Storm",
            "Nasty Plot",
            "Sucker Punch"
        ],
        "evs": {
            "atk": 0
        },
        "ivs": {
            "atk": 0
        },
        "types": [
            "grass",
            "dark"
        ]
    },
    "Shiinotic": {
        "level": 86,
        "abilities": [
            "Effect Spore"
        ],
        "items": [
            "Leftovers"
        ],
        "moves": [
            "Energy Ball",
            "Leech Seed",
            "Moonblast",
            "Spore",
            "Strength Sap"
        ],
        "evs": {
            "atk": 0
        },
        "ivs": {
            "atk": 0
        },
        "types": [
            "grass",
            "fairy"
        ]
    },
    "Tangrowth": {
        "level": 84,
        "abilities": [
            "Regenerator"
        ],
        "items": [
            "Assault Vest",
            "Rocky Helmet"
        ],
        "moves": [
            "Earthquake",
            "Giga Drain",
            "Knock Off",
            "Leech Seed",
            "Sleep Powder",
            "Sludge Bomb"
        ],
        "evs": {
            "atk": 0
        },
        "ivs": {
            "atk": 0
        },
        "types": [
            "grass"
        ]
    },
    "Trevenant": {
        "level": 86,
        "abilities": [
            "Natural Cure"
        ],
        "items": [
            "Choice Band",
            "Life Orb"
        ],
        "moves": [
            "Earthquake",
            "Horn Leech",
            "Poltergeist",
            "Rock Slide",
            "Trick Room",
            "Wood Hammer"
        ],
        "evs": {
            "spe": 0
        },
        "ivs": {
            "spe": 0
        },
        "types": [
            "ghost",
            "grass"
        ]
    },
    "Tsareena": {
        "level": 84,
        "abilities": [
            "Queenly Majesty"
        ],
        "items": [
            "Assault Vest",
            "Choice Band",
            "Choice Scarf",
            "Heavy-Duty Boots",
            "Leftovers",
            "Life Orb"
        ],
        "moves": [
            "High Jump Kick",
            "Knock Off",
            "Power Whip",
            "Rapid Spin",
            "Synthesis",
            "Triple Axel",
            "U-turn"
        ],
        "types": [
            "grass"
        ]
    },
    "Venusaur": {
        "level": 82,
        "abilities": [
            "Chlorophyll",
            "Overgrow"
        ],
        "items": [
            "Black Sludge"
        ],
        "moves": [
            "Giga Drain",
            "Leech Seed",
            "Sleep Powder",
            "Sludge Bomb",
            "Substitute"
        ],
        "evs": {
            "atk": 0
        },
        "ivs": {
            "atk": 0
        },
        "types": [
            "grass",
            "poison"
        ]
    },
    "Vileplume": {
        "level": 84,
        "abilities": [
            "Chlorophyll",
            "Effect Spore"
        ],
        "items": [
            "Black Sludge"
        ],
        "moves": [
            "Aromatherapy",
            "Giga Drain",
            "Sleep Powder",
            "Sludge Bomb",
            "Strength Sap"
        ],
        "evs": {
            "atk": 0
        },
        "ivs": {
            "atk": 0
        },
        "types": [
            "grass",
            "poison"
        ]
    },
    "Virizion": {
        "level": 82,
        "abilities": [
            "Justified"
        ],
        "items": [
            "Lum Berry"
        ],
        "moves": [
            "Close Combat",
            "Leaf Blade",
            "Stone Edge",
            "Swords Dance"
        ],
        "types": [
            "grass",
            "fighting"
        ]
    },
    "Whimsicott": {
        "level": 84,
        "abilities": [
            "Prankster"
        ],
        "items": [
            "Leftovers"
        ],
        "moves": [
            "Defog",
            "Energy Ball",
            "Leech Seed",
            "Moonblast",
            "Stun Spore",
            "Taunt",
            "U-turn"
        ],
        "evs": {
            "atk": 0
        },
        "ivs": {
            "atk": 0
        },
        "types": [
            "grass",
            "fairy"
        ]
    },
    "Zarude": {
        "level": 78,
        "abilities": [
            "Leaf Guard"
        ],
        "items": [
            "Choice Band",
            "Choice Scarf",
            "Leftovers"
        ],
        "moves": [
            "Bulk Up",
            "Close Combat",
            "Darkest Lariat",
            "Jungle Healing",
            "Power Whip",
            "U-turn"
        ],
        "types": [
            "dark",
            "grass"
        ]
    }
}