{"Arceus-Ghost": {"level": 74, "abilities": ["Multitype"], "items": ["Spooky Plate"], "moves": ["Calm Mind", "Focus Blast", "Judgment", "Recover", "Will-O-Wisp"], "evs": {"atk": 0}, "ivs": {"atk": 0}, "types": ["ghost"]}, "Banette": {"level": 88, "abilities": ["Insomnia"], "items": ["Focus Sash", "Leftovers", "Life Orb"], "moves": ["Destiny Bond", "Hidden Power Fighting", "Shadow Claw", "Shadow Sneak", "Taunt", "Thunder Wave", "Will-O-Wisp"], "types": ["ghost"]}, "Drifblim": {"level": 88, "abilities": ["Unburden"], "items": ["Chesto Berry", "Sitrus Berry"], "moves": ["Calm Mind", "Hidden Power Fighting", "Rest", "Shadow Ball", "Substitute", "Thunderbolt"], "evs": {"atk": 0}, "types": ["ghost", "flying"]}, "Dusknoir": {"level": 82, "abilities": ["Pressure"], "items": ["Expert Belt", "Leftovers", "Life Orb"], "moves": ["Earthquake", "Focus Punch", "Ice Beam", "Pain Split", "Shadow Sneak", "Substitute", "Will-O-Wisp"], "types": ["ghost"]}, "Froslass": {"level": 82, "abilities": ["Snow Cloak"], "items": ["Focus Sash", "Leftovers"], "moves": ["Destiny Bond", "Ice Beam", "Shadow Ball", "Spikes", "Taunt"], "evs": {"atk": 0}, "ivs": {"atk": 0}, "types": ["ice", "ghost"]}, "Gengar": {"level": 80, "abilities": ["Levitate"], "items": ["Black Sludge", "Choice Specs", "Focus Sash", "Life Orb"], "moves": ["Focus Blast", "Hidden Power Fire", "Hypnosis", "Pain Split", "Shadow Ball", "Sludge Bomb", "Substitute", "Thunderbolt", "Trick"], "evs": {"atk": 0}, "types": ["ghost", "poison"]}, "Giratina": {"level": 76, "abilities": ["Pressure"], "items": ["Chesto Berry", "Leftovers"], "moves": ["Calm Mind", "Dragon Pulse", "Rest", "Roar", "Shadow Ball", "Sleep Talk", "Will-O-Wisp"], "evs": {"atk": 0}, "ivs": {"atk": 0}, "types": ["ghost", "dragon"]}, "Giratina-Origin": {"level": 76, "abilities": ["Levitate"], "items": ["Griseous Orb"], "moves": ["Aura Sphere", "Calm Mind", "Draco Meteor", "Dragon Pulse", "Hidden Power Fire", "Outrage", "Shadow Ball", "Shadow Sneak", "Substitute"], "evs": {"atk": 0}, "types": ["ghost", "dragon"]}, "Mismagius": {"level": 84, "abilities": ["Levitate"], "items": ["Leftovers", "Life Orb"], "moves": ["Hidden Power Fighting", "Nasty Plot", "Pain Split", "Shadow Ball", "Substitute", "Taunt", "Thunderbolt", "Will-O-Wisp"], "evs": {"atk": 0}, "types": ["ghost"]}, "Rotom": {"level": 84, "abilities": ["Levitate"], "items": ["Choice Scarf", "Choice Specs", "Focus Sash", "Leftovers", "Life Orb"], "moves": ["Hidden Power Fighting", "Hidden Power Ice", "Pain Split", "Shadow Ball", "Substitute", "Thunderbolt", "Trick", "Will-O-Wisp"], "evs": {"atk": 0}, "types": ["electric", "ghost"]}, "Sableye": {"level": 88, "abilities": ["Keen Eye"], "items": ["Leftovers"], "moves": ["Night Shade", "Recover", "Seismic Toss", "Taunt", "Toxic", "Will-O-Wisp"], "evs": {"atk": 0}, "ivs": {"atk": 0}, "types": ["dark", "ghost"]}, "Shedinja": {"level": 88, "abilities": ["Wonder Guard"], "items": ["Focus Sash"], "moves": ["Shadow Sneak", "Sucker Punch", "Swords Dance", "Will-O-Wisp", "X-Scissor"], "types": ["bug", "ghost"]}, "Spiritomb": {"level": 84, "abilities": ["Pressure"], "items": ["Chesto Berry", "Leftovers"], "moves": ["Calm Mind", "Dark Pulse", "Hidden Power Fighting", "Rest", "Sleep Talk", "Will-O-Wisp"], "evs": {"atk": 0}, "types": ["ghost", "dark"]}}